mdxpy/__init__.py
mdxpy/mdx.py
mdxpy-0.3.dist-info/LICENSE
mdxpy-0.3.dist-info/METADATA
mdxpy-0.3.dist-info/WHEEL
mdxpy-0.3.dist-info/top_level.txt
mdxpy-0.3.dist-info/RECORD
