Metadata-Version: 2.1
Name: mdxpy
Version: 0.3
Summary: A simple, yet elegant MDX library for TM1
Home-page: https://github.com/cubewise-code/mdxpy
Maintainer: Marius Wirtz
Maintainer-email: MWirtz@cubewise.com
License: MIT-LICENSE
Keywords: MDX,TM1,IBM Cognos TM1,Planning Analytics,PA,Cognos
Platform: any
Classifier: Intended Audience :: Developers
Classifier: License :: OSI Approved :: MIT License
Classifier: Programming Language :: Python
Classifier: Programming Language :: Python :: 3
Classifier: Programming Language :: Python :: 3.5
Classifier: Programming Language :: Python :: 3.6
Classifier: Programming Language :: Python :: 3.7
Classifier: Programming Language :: Python :: 3.8
Classifier: Programming Language :: Python :: 3.9
Classifier: Programming Language :: Python :: Implementation :: CPython
Requires-Python: >=3.5
